{"otherData": {},"traceEvents":[{"cat":"function","dur":46,"name":"void __cdecl Hazel::OpenGLVertexArray::AddVertexBuffer(const class std::shared_ptr<class Hazel::VertexBuffer> &)","ph":"X","pid":0,"tid":1736734651,"ts":83226339981},{"cat":"function","dur":58,"name":"void __cdecl Hazel::OpenGLVertexArray::AddVertexBuffer(const class std::shared_ptr<class Hazel::VertexBuffer> &)","ph":"X","pid":0,"tid":1736734651,"ts":83226341380},{"cat":"function","dur":22,"name":"void __cdecl Hazel::OpenGLVertexArray::AddVertexBuffer(const class std::shared_ptr<class Hazel::VertexBuffer> &)","ph":"X","pid":0,"tid":1736734651,"ts":83226341950}]}